

[
    {
        "id":1,
        "image": "/assets/images/Cherry-Parfait-rose.jpg",
        "variety":"Cherry Parfait"
    },
    {
        "id":2,
        "image": "/assets/images/Flower-Carpet-Amber.jpg",
        "variety": "Flower Carpet Amber"
    },
    {
        "id":3,
        "image": "/assets/images/Iceberg-rose.jpg",
        "variety": "Iceberg"
    },
    {
        "id":4,
        "image": "/assets/images/Julia-child-rose.jpg",
        "variety": "Julia Child"
    },
    {
        "id":5,
        "image": "/assets/images/Lady-Emma-Hamilton-rose.jpg",
        "variety": "Lady Emma Hamilton"
    },
    {
        "id":6,
        "image": "/assets/images/Louis-Philippe.jpg",
        "variety": "Louis Philippe"
    },
    {
        "id":7,
        "image": "/assets/images/Princess-Alexandra-of-Kent.jpg",
        "variety": "Princess Alexandra of Kent"
    },
    {
        "id":8,
        "image": "/assets/images/Rosa-Charles-de-Mills.jpg",
        "variety":"Charles de Mills"
    },
    {
        "id":9,
        "image": "/assets/images/Rosa-Duchesse-de-Brabant.jpg",
        "variety":"Duchesse de Brabant"
    },
    {
        "id":10,
        "image": "/assets/images/Rosa-Flower-Carpet-Scarlet.jpg",
        "variety":"Flower Carpet Scarlet"
    },
    {
        "id":11,
        "image": "/assets/images/Rosa-Madame-Isaac-Pereire.jpg",
        "variety": "Madame Isaac Pereire"
    },
    {
        "id":12,
        "image": "/assets/images/Rosa-Milkmaid.jpg",
        "variety":"Milkmaid"
    }
]

